pyscada/__init__.py
pyscada/scripting/__init__.py
pyscada/scripting/admin.py
pyscada/scripting/apps.py
pyscada/scripting/models.py
pyscada/scripting/signals.py
pyscada/scripting/worker.py
pyscada/scripting/migrations/0001_initial.py
pyscada/scripting/migrations/__init__.py
pyscada_scripting-0.8.0.dist-info/AUTHORS
pyscada_scripting-0.8.0.dist-info/LICENSE
pyscada_scripting-0.8.0.dist-info/METADATA
pyscada_scripting-0.8.0.dist-info/WHEEL
pyscada_scripting-0.8.0.dist-info/top_level.txt
pyscada_scripting-0.8.0.dist-info/RECORD
