Metadata-Version: 1.1
Name: pyscada-scripting
Version: 0.8.0
Summary: Scripting extension for PyScada a Python and Django based Open Source SCADA System
Home-page: http://www.github.com/pyscada/PyScada-Scripting
Author: Martin Schröder, Camille Lavayssiere
Author-email: team@pyscada.org
License: AGPLv3
Platform: OS Independent
Classifier: Development Status :: 4 - Beta
Classifier: Environment :: Web Environment
Classifier: Environment :: Console
Classifier: Framework :: Django
Classifier: Intended Audience :: Developers
Classifier: Intended Audience :: Science/Research
Classifier: License :: OSI Approved :: GNU Affero General Public License v3 or later (AGPLv3+)
Classifier: Operating System :: POSIX
Classifier: Operating System :: MacOS :: MacOS X
Classifier: Programming Language :: Python
Classifier: Programming Language :: JavaScript
Classifier: Topic :: Internet :: WWW/HTTP :: Dynamic Content
Classifier: Topic :: Scientific/Engineering :: Visualization
